emojit/__init__.py
emojit/emoji_digit_codec.py
emojit-1.1.0.dist-info/LICENSE
emojit-1.1.0.dist-info/METADATA
emojit-1.1.0.dist-info/WHEEL
emojit-1.1.0.dist-info/RECORD
