Metadata-Version: 2.1
Name: emojit
Version: 1.1.0
Summary: Support for emoji digits in Python
Author: Ivan Dmitrievskii
Author-email: yellow.iron9441@headless.place
Requires-Python: >=3.9,<4.0
Classifier: Programming Language :: Python :: 3
Classifier: Programming Language :: Python :: 3.9
Classifier: Programming Language :: Python :: 3.10
Classifier: Programming Language :: Python :: 3.11
Classifier: Programming Language :: Python :: 3.12
Classifier: Programming Language :: Python :: 3.13
